Workbook

Sheet Summary
A1: NorthStar Supply Co. — Inventory & Supply Chain Summary
A2: 2024-2025, 150 SKUs, 10 suppliers. Synthetic data generated for a portfolio project.
A5: CURRENT PERFORMANCE (2024-2025)
A6: Total revenue | B6: 21128847 | C6: Source: fact_sales
A7: Gross margin | B7: 0.38
A8: Revenue growth 2025 vs 2024 | B8: -0.0201 | C8: Demand grew ~2% but sales fell: stockouts rose in 2025
A9: Inventory turnover (annual) | B9: 11.59 | C9: Annual COGS / average inventory value
A10: Days of inventory | B10: 31.5
A11: Stockout rate (% of SKU-days) | B11: 0.0563
A12: Fill rate (% of demand met) | B12: 0.9429
A13: Est. revenue lost to stockouts | B13: 2337184 | C13: Lost units x list price
A14: Supplier OTIF | B14: 0.5392 | C14: On-time AND in-full
A16: RECOMMENDED POLICY (2025 back-test)
A17: Stockout rate: optimized (current at right) | B17: ='Policy Backtest'!C5 | C17: ='Policy Backtest'!B5
A18: Revenue recovered vs current policy | B18: =-'Policy Backtest'!D8 | C18: Lost revenue avoided in 2025
A19: Change in avg inventory value | B19: ='Policy Backtest'!E10 | C19: Fewer stockouts AND less capital tied up
A20: Purchase orders: change | B20: ='Policy Backtest'!E12
A22: ACTION LIST TODAY
A23: SKUs to reorder now | B23: =COUNTIF('Replenishment Plan'!Y5:Y154,"REORDER NOW") | C23: See Replenishment Plan, filter column Y
A24: Suggested order value ($) | B24: =SUMPRODUCT('Replenishment Plan'!Z5:Z154,'Replenishment Plan'!G5:G154)
A25: SKUs flagged as excess | B25: =COUNTIF('Replenishment Plan'!Y5:Y154,"EXCESS*")
A26: Excess inventory value ($) | B26: =SUM('Replenishment Plan'!X5:X154) | C26: Candidates for promotion, transfer or return-to-vendor
A27: Critical suppliers (OTIF < 45%) | B27: =COUNTIF('Supplier Scorecard'!N5:N14,"Critical")
A29: Colour key: blue = data from the pipeline, black = formula, green = link to another sheet.

Sheet Assumptions
A1: Assumptions
A2: Blue text on yellow = inputs you can change. Every formula in the workbook reads from here.
A4: Assumption | B4: Value | C4: Note
A5: Order cost per PO ($) | B5: 75 | C5: Admin, receiving and fixed freight per purchase order. Industry rule of thumb; replace with your actual figure.
A6: Annual holding cost (% of unit cost) | B6: 0.25 | C6: Capital, storage, insurance, obsolescence. 20-30% is the common range.
A7: Service level: A items | B7: 0.98 | C7: Probability of not stocking out during a replenishment cycle.
A8: Service level: B items | B8: 0.95
A9: Service level: C items | B9: 0.9
A10: Excess threshold (days of cover) | B10: 120 | C10: On-hand above this many days of forecast demand is flagged as excess.
A12: Class | B12: Service level | C12: Lookup table used by the Replenishment Plan (do not edit; change B7:B9 instead).
A13: A | B13: =B7
A14: B | B14: =B8
A15: C | B15: =B9

Sheet Replenishment Plan
A1: Replenishment Plan (as of 2026-01-01)
A2: Blue = data inputs from the Python pipeline. Black = live formulas. Change Assumptions to re-plan.
A4: Product ID | B4: Product | C4: Category | D4: Supplier | E4: ABC | F4: XYZ | G4: Unit cost ($) | H4: Daily demand (units) | I4: Demand std dev | J4: Lead time (days) | K4: Lead time std dev | L4: MOQ | M4: On hand | N4: On order | O4: Service level | P4: Z score | Q4: Safety stock | R4: Reorder point | S4: EOQ | T4: Order qty | U4: Inventory position | V4: Days of cover | W4: Excess units | X4: Excess value ($) | Y4: Action | Z4: Suggested order
A5: P0001 | B5: Electronics Item 001 | C5: Electronics | D5: S01 | E5: A | F5: X | G5: 146.97 | H5: 12.439 | I5: 4.895 | J5: 7.124 | K5: 1.029 | L5: 24 | M5: 651 | N5: 0 | O5: =INDEX(Assumptions!$B$13:$B$15,MATCH(E5,Assumptions!$A$13:$A$15,0)) | P5: =NORMSINV(O5) | Q5: =ROUNDUP(P5*SQRT(J5*I5^2+H5^2*K5^2),0) | R5: =ROUNDUP(H5*J5+Q5,0) | S5: =IF(H5>0,ROUNDUP(SQRT(2*H5*365*Assumptions!$B$5/(Assumptions!$B$6*G5)),0),0) | T5: =MAX(S5,L5) | U5: =M5+N5 | V5: =IF(H5>0,M5/H5,999) | W5: =MAX(0,U5-MAX(R5+T5,H5*Assumptions!$B$10)) | X5: =W5*G5 | Y5: =IF(U5<=R5,"REORDER NOW",IF(W5>0,"EXCESS - pause orders / promote","OK")) | Z5: =IF(Y5="REORDER NOW",T5,0)
A6: P0002 | B6: Electronics Item 002 | C6: Electronics | D6: S07 | E6: A | F6: X | G6: 22.72 | H6: 5.037 | I6: 3.075 | J6: 14.688 | K6: 2.076 | L6: 100 | M6: 0 | N6: 207 | O6: =INDEX(Assumptions!$B$13:$B$15,MATCH(E6,Assumptions!$A$13:$A$15,0)) | P6: =NORMSINV(O6) | Q6: =ROUNDUP(P6*SQRT(J6*I6^2+H6^2*K6^2),0) | R6: =ROUNDUP(H6*J6+Q6,0) | S6: =IF(H6>0,ROUNDUP(SQRT(2*H6*365*Assumptions!$B$5/(Assumptions!$B$6*G6)),0),0) | T6: =MAX(S6,L6) | U6: =M6+N6 | V6: =IF(H6>0,M6/H6,999) | W6: =MAX(0,U6-MAX(R6+T6,H6*Assumptions!$B$10)) | X6: =W6*G6 | Y6: =IF(U6<=R6,"REORDER NOW",IF(W6>0,"EXCESS - pause orders / promote","OK")) | Z6: =IF(Y6="REORDER NOW",T6,0)
A7: P0003 | B7: Electronics Item 003 | C7: Electronics | D7: S06 | E7: A | F7: X | G7: 173.91 | H7: 3.051 | I7: 2.692 | J7: 13.277 | K7: 2.821 | L7: 48 | M7: 72 | N7: 0 | O7: =INDEX(Assumptions!$B$13:$B$15,MATCH(E7,Assumptions!$A$13:$A$15,0)) | P7: =NORMSINV(O7) | Q7: =ROUNDUP(P7*SQRT(J7*I7^2+H7^2*K7^2),0) | R7: =ROUNDUP(H7*J7+Q7,0) | S7: =IF(H7>0,ROUNDUP(SQRT(2*H7*365*Assumptions!$B$5/(Assumptions!$B$6*G7)),0),0) | T7: =MAX(S7,L7) | U7: =M7+N7 | V7: =IF(H7>0,M7/H7,999) | W7: =MAX(0,U7-MAX(R7+T7,H7*Assumptions!$B$10)) | X7: =W7*G7 | Y7: =IF(U7<=R7,"REORDER NOW",IF(W7>0,"EXCESS - pause orders / promote","OK")) | Z7: =IF(Y7="REORDER NOW",T7,0)
A8: P0004 | B8: Electronics Item 004 | C8: Electronics | D8: S04 | E8: A | F8: X | G8: 188.17 | H8: 0.991 | I8: 1.458 | J8: 39.643 | K8: 7.265 | L8: 200 | M8: 126 | N8: 0 | O8: =INDEX(Assumptions!$B$13:$B$15,MATCH(E8,Assumptions!$A$13:$A$15,0)) | P8: =NORMSINV(O8) | Q8: =ROUNDUP(P8*SQRT(J8*I8^2+H8^2*K8^2),0) | R8: =ROUNDUP(H8*J8+Q8,0) | S8: =IF(H8>0,ROUNDUP(SQRT(2*H8*365*Assumptions!$B$5/(Assumptions!$B$6*G8)),0),0) | T8: =MAX(S8,L8) | U8: =M8+N8 | V8: =IF(H8>0,M8/H8,999) | W8: =MAX(0,U8-MAX(R8+T8,H8*Assumptions!$B$10)) | X8: =W8*G8 | Y8: =IF(U8<=R8,"REORDER NOW",IF(W8>0,"EXCESS - pause orders / promote","OK")) | Z8: =IF(Y8="REORDER NOW",T8,0)
A9: P0006 | B9: Electronics Item 006 | C9: Electronics | D9: S01 | E9: A | F9: X | G9: 150.75 | H9: 4.405 | I9: 2.745 | J9: 7.124 | K9: 1.029 | L9: 24 | M9: 41 | N9: 0 | O9: =INDEX(Assumptions!$B$13:$B$15,MATCH(E9,Assumptions!$A$13:$A$15,0)) | P9: =NORMSINV(O9) | Q9: =ROUNDUP(P9*SQRT(J9*I9^2+H9^2*K9^2),0) | R9: =ROUNDUP(H9*J9+Q9,0) | S9: =IF(H9>0,ROUNDUP(SQRT(2*H9*365*Assumptions!$B$5/(Assumptions!$B$6*G9)),0),0) | T9: =MAX(S9,L9) | U9: =M9+N9 | V9: =IF(H9>0,M9/H9,999) | W9: =MAX(0,U9-MAX(R9+T9,H9*Assumptions!$B$10)) | X9: =W9*G9 | Y9: =IF(U9<=R9,"REORDER NOW",IF(W9>0,"EXCESS - pause orders / promote","OK")) | Z9: =IF(Y9="REORDER NOW",T9,0)
A10: P0007 | B10: Electronics Item 007 | C10: Electronics | D10: S07 | E10: A | F10: X | G10: 41.52 | H10: 4.324 | I10: 3.141 | J10: 14.688 | K10: 2.076 | L10: 100 | M10: 481 | N10: 0 | O10: =INDEX(Assumptions!$B$13:$B$15,MATCH(E10,Assumptions!$A$13:$A$15,0)) | P10: =NORMSINV(O10) | Q10: =ROUNDUP(P10*SQRT(J10*I10^2+H10^2*K10^2),0) | R10: =ROUNDUP(H10*J10+Q10,0) | S10: =IF(H10>0,ROUNDUP(SQRT(2*H10*365*Assumptions!$B$5/(Assumptions!$B$6*G10)),0),0) | T10: =MAX(S10,L10) | U10: =M10+N10 | V10: =IF(H10>0,M10/H10,999) | W10: =MAX(0,U10-MAX(R10+T10,H10*Assumptions!$B$10)) | X10: =W10*G10 | Y10: =IF(U10<=R10,"REORDER NOW",IF(W10>0,"EXCESS - pause orders / promote","OK")) | Z10: =IF(Y10="REORDER NOW",T10,0)
A11: P0012 | B11: Electronics Item 012 | C11: Electronics | D11: S03 | E11: A | F11: X | G11: 115.73 | H11: 5.393 | I11: 3.343 | J11: 5.124 | K11: 0.839 | L11: 12 | M11: 177 | N11: 0 | O11: =INDEX(Assumptions!$B$13:$B$15,MATCH(E11,Assumptions!$A$13:$A$15,0)) | P11: =NORMSINV(O11) | Q11: =ROUNDUP(P11*SQRT(J11*I11^2+H11^2*K11^2),0) | R11: =ROUNDUP(H11*J11+Q11,0) | S11: =IF(H11>0,ROUNDUP(SQRT(2*H11*365*Assumptions!$B$5/(Assumptions!$B$6*G11)),0),0) | T11: =MAX(S11,L11) | U11: =M11+N11 | V11: =IF(H11>0,M11/H11,999) | W11: =MAX(0,U11-MAX(R11+T11,H11*Assumptions!$B$10)) | X11: =W11*G11 | Y11: =IF(U11<=R11,"REORDER NOW",IF(W11>0,"EXCESS - pause orders / promote","OK")) | Z11: =IF(Y11="REORDER NOW",T11,0)
A12: P0013 | B12: Electronics Item 013 | C12: Electronics | D12: S05 | E12: A | F12: X | G12: 131.65 | H12: 4.085 | I12: 2.607 | J12: 8.19 | K12: 1.086 | L12: 24 | M12: 45 | N12: 0 | O12: =INDEX(Assumptions!$B$13:$B$15,MATCH(E12,Assumptions!$A$13:$A$15,0)) | P12: =NORMSINV(O12) | Q12: =ROUNDUP(P12*SQRT(J12*I12^2+H12^2*K12^2),0) | R12: =ROUNDUP(H12*J12+Q12,0) | S12: =IF(H12>0,ROUNDUP(SQRT(2*H12*365*Assumptions!$B$5/(Assumptions!$B$6*G12)),0),0) | T12: =MAX(S12,L12) | U12: =M12+N12 | V12: =IF(H12>0,M12/H12,999) | W12: =MAX(0,U12-MAX(R12+T12,H12*Assumptions!$B$10)) | X12: =W12*G12 | Y12: =IF(U12<=R12,"REORDER NOW",IF(W12>0,"EXCESS - pause orders / promote","OK")) | Z12: =IF(Y12="REORDER NOW",T12,0)
A13: P0016 | B13: Electronics Item 016 | C13: Electronics | D13: S08 | E13: A | F13: X | G13: 99.55 | H13: 1.333 | I13: 1.826 | J13: 9.132 | K13: 1.033 | L13: 12 | M13: 27 | N13: 0 | O13: =INDEX(Assumptions!$B$13:$B$15,MATCH(E13,Assumptions!$A$13:$A$15,0)) | P13: =NORMSINV(O13) | Q13: =ROUNDUP(P13*SQRT(J13*I13^2+H13^2*K13^2),0) | R13: =ROUNDUP(H13*J13+Q13,0) | S13: =IF(H13>0,ROUNDUP(SQRT(2*H13*365*Assumptions!$B$5/(Assumptions!$B$6*G13)),0),0) | T13: =MAX(S13,L13) | U13: =M13+N13 | V13: =IF(H13>0,M13/H13,999) | W13: =MAX(0,U13-MAX(R13+T13,H13*Assumptions!$B$10)) | X13: =W13*G13 | Y13: =IF(U13<=R13,"REORDER NOW",IF(W13>0,"EXCESS - pause orders / promote","OK")) | Z13: =IF(Y13="REORDER NOW",T13,0)
A14: P0018 | B14: Electronics Item 018 | C14: Electronics | D14: S02 | E14: A | F14: X | G14: 113.46 | H14: 5.6 | I14: 3.864 | J14: 10.431 | K14: 1.544 | L14: 50 | M14: 124 | N14: 0 | O14: =INDEX(Assumptions!$B$13:$B$15,MATCH(E14,Assumptions!$A$13:$A$15,0)) | P14: =NORMSINV(O14) | Q14: =ROUNDUP(P14*SQRT(J14*I14^2+H14^2*K14^2),0) | R14: =ROUNDUP(H14*J14+Q14,0) | S14: =IF(H14>0,ROUNDUP(SQRT(2*H14*365*Assumptions!$B$5/(Assumptions!$B$6*G14)),0),0) | T14: =MAX(S14,L14) | U14: =M14+N14 | V14: =IF(H14>0,M14/H14,999) | W14: =MAX(0,U14-MAX(R14+T14,H14*Assumptions!$B$10)) | X14: =W14*G14 | Y14: =IF(U14<=R14,"REORDER NOW",IF(W14>0,"EXCESS - pause orders / promote","OK")) | Z14: =IF(Y14="REORDER NOW",T14,0)
A15: P0019 | B15: Electronics Item 019 | C15: Electronics | D15: S01 | E15: A | F15: X | G15: 130.29 | H15: 6.16 | I15: 3.738 | J15: 7.124 | K15: 1.029 | L15: 24 | M15: 225 | N15: 0 | O15: =INDEX(Assumptions!$B$13:$B$15,MATCH(E15,Assumptions!$A$13:$A$15,0)) | P15: =NORMSINV(O15) | Q15: =ROUNDUP(P15*SQRT(J15*I15^2+H15^2*K15^2),0) | R15: =ROUNDUP(H15*J15+Q15,0) | S15: =IF(H15>0,ROUNDUP(SQRT(2*H15*365*Assumptions!$B$5/(Assumptions!$B$6*G15)),0),0) | T15: =MAX(S15,L15) | U15: =M15+N15 | V15: =IF(H15>0,M15/H15,999) | W15: =MAX(0,U15-MAX(R15+T15,H15*Assumptions!$B$10)) | X15: =W15*G15 | Y15: =IF(U15<=R15,"REORDER NOW",IF(W15>0,"EXCESS - pause orders / promote","OK")) | Z15: =IF(Y15="REORDER NOW",T15,0)
A16: P0020 | B16: Electronics Item 020 | C16: Electronics | D16: S06 | E16: A | F16: X | G16: 59.66 | H16: 7.045 | I16: 3.479 | J16: 13.277 | K16: 2.821 | L16: 48 | M16: 51 | N16: 126 | O16: =INDEX(Assumptions!$B$13:$B$15,MATCH(E16,Assumptions!$A$13:$A$15,0)) | P16: =NORMSINV(O16) | Q16: =ROUNDUP(P16*SQRT(J16*I16^2+H16^2*K16^2),0) | R16: =ROUNDUP(H16*J16+Q16,0) | S16: =IF(H16>0,ROUNDUP(SQRT(2*H16*365*Assumptions!$B$5/(Assumptions!$B$6*G16)),0),0) | T16: =MAX(S16,L16) | U16: =M16+N16 | V16: =IF(H16>0,M16/H16,999) | W16: =MAX(0,U16-MAX(R16+T16,H16*Assumptions!$B$10)) | X16: =W16*G16 | Y16: =IF(U16<=R16,"REORDER NOW",IF(W16>0,"EXCESS - pause orders / promote","OK")) | Z16: =IF(Y16="REORDER NOW",T16,0)
... A154: P0150 | B154: Packaging Item 150 | C154: Packaging | D154: S07 | E154: C | F154: X | G154: 1.81 | H154: 11.385 | I154: 2.809 | J154: 14.688 | K154: 2.076 | L154: 100 | M154: 75 | N154: 815 | O154: =INDEX(Assumptions!$B$13:$B$15,MATCH(E154,Assumptions!$A$13:$A$15,0)) | P154: =NORMSINV(O154) | Q154: =ROUNDUP(P154*SQRT(J154*I154^2+H154^2*K154^2),0) | R154: =ROUNDUP(H154*J154+Q154,0) | S154: =IF(H154>0,ROUNDUP(SQRT(2*H154*365*Assumptions!$B$5/(Assumptions!$B$6*G154)),0),0) | T154: =MAX(S154,L154) | U154: =M154+N154 | V154: =IF(H154>0,M154/H154,999) | W154: =MAX(0,U154-MAX(R154+T154,H154*Assumptions!$B$10)) | X154: =W154*G154 | Y154: =IF(U154<=R154,"REORDER NOW",IF(W154>0,"EXCESS - pause orders / promote","OK")) | Z154: =IF(Y154="REORDER NOW",T154,0)

Sheet ABC Analysis
A1: ABC-XYZ Classification
A2: A = top 80% of revenue, B = next 15%, C = last 5%. X/Y/Z = demand CV <0.5 / 0.5-1.0 / >1.0.
A4: Product ID | B4: Product | C4: Category | D4: Revenue ($) | E4: Share of revenue | F4: Cumulative share | G4: ABC (formula) | H4: Demand CV | I4: XYZ | J4: ABC-XYZ | L4: Class | M4: Products | N4: % of SKUs | O4: % of revenue
A5: P0001 | B5: Electronics Item 001 | C5: Electronics | D5: 2119523.4 | E5: =D5/SUM($D$5:$D$154) | F5: =SUM($D$5:D5)/SUM($D$5:$D$154) | G5: =IF(F5<=0.8,"A",IF(F5<=0.95,"B","C")) | H5: 0.256 | I5: X | J5: =G5&I5 | L5: A | M5: =COUNTIF($G$5:$G$154,L5) | N5: =M5/COUNTA($A$5:$A$154) | O5: =SUMIF($G$5:$G$154,L5,$D$5:$D$154)/SUM($D$5:$D$154)
A6: P0067 | B6: Outdoor Item 067 | C6: Outdoor & Garden | D6: 1175448.1 | E6: =D6/SUM($D$5:$D$154) | F6: =SUM($D$5:D6)/SUM($D$5:$D$154) | G6: =IF(F6<=0.8,"A",IF(F6<=0.95,"B","C")) | H6: 0.519 | I6: Y | J6: =G6&I6 | L6: B | M6: =COUNTIF($G$5:$G$154,L6) | N6: =M6/COUNTA($A$5:$A$154) | O6: =SUMIF($G$5:$G$154,L6,$D$5:$D$154)/SUM($D$5:$D$154)
A7: P0019 | B7: Electronics Item 019 | C7: Electronics | D7: 1081617.4 | E7: =D7/SUM($D$5:$D$154) | F7: =SUM($D$5:D7)/SUM($D$5:$D$154) | G7: =IF(F7<=0.8,"A",IF(F7<=0.95,"B","C")) | H7: 0.307 | I7: X | J7: =G7&I7 | L7: C | M7: =COUNTIF($G$5:$G$154,L7) | N7: =M7/COUNTA($A$5:$A$154) | O7: =SUMIF($G$5:$G$154,L7,$D$5:$D$154)/SUM($D$5:$D$154)
A8: P0044 | B8: Home Item 044 | C8: Home & Kitchen | D8: 1039405.1 | E8: =D8/SUM($D$5:$D$154) | F8: =SUM($D$5:D8)/SUM($D$5:$D$154) | G8: =IF(F8<=0.8,"A",IF(F8<=0.95,"B","C")) | H8: 0.542 | I8: Y | J8: =G8&I8
A9: P0006 | B9: Electronics Item 006 | C9: Electronics | D9: 929884.99 | E9: =D9/SUM($D$5:$D$154) | F9: =SUM($D$5:D9)/SUM($D$5:$D$154) | G9: =IF(F9<=0.8,"A",IF(F9<=0.95,"B","C")) | H9: 0.294 | I9: X | J9: =G9&I9
A10: P0012 | B10: Electronics Item 012 | C10: Electronics | D10: 697510.99 | E10: =D10/SUM($D$5:$D$154) | F10: =SUM($D$5:D10)/SUM($D$5:$D$154) | G10: =IF(F10<=0.8,"A",IF(F10<=0.95,"B","C")) | H10: 0.335 | I10: X | J10: =G10&I10
A11: P0018 | B11: Electronics Item 018 | C11: Electronics | D11: 661094.81 | E11: =D11/SUM($D$5:$D$154) | F11: =SUM($D$5:D11)/SUM($D$5:$D$154) | G11: =IF(F11<=0.8,"A",IF(F11<=0.95,"B","C")) | H11: 0.278 | I11: X | J11: =G11&I11
A12: P0003 | B12: Electronics Item 003 | C12: Electronics | D12: 629992 | E12: =D12/SUM($D$5:$D$154) | F12: =SUM($D$5:D12)/SUM($D$5:$D$154) | G12: =IF(F12<=0.8,"A",IF(F12<=0.95,"B","C")) | H12: 0.28 | I12: X | J12: =G12&I12
A13: P0064 | B13: Outdoor Item 064 | C13: Outdoor & Garden | D13: 599322.71 | E13: =D13/SUM($D$5:$D$154) | F13: =SUM($D$5:D13)/SUM($D$5:$D$154) | G13: =IF(F13<=0.8,"A",IF(F13<=0.95,"B","C")) | H13: 0.43 | I13: X | J13: =G13&I13
A14: P0054 | B14: Home Item 054 | C14: Home & Kitchen | D14: 595993.44 | E14: =D14/SUM($D$5:$D$154) | F14: =SUM($D$5:D14)/SUM($D$5:$D$154) | G14: =IF(F14<=0.8,"A",IF(F14<=0.95,"B","C")) | H14: 0.279 | I14: X | J14: =G14&I14
A15: P0013 | B15: Electronics Item 013 | C15: Electronics | D15: 572261.65 | E15: =D15/SUM($D$5:$D$154) | F15: =SUM($D$5:D15)/SUM($D$5:$D$154) | G15: =IF(F15<=0.8,"A",IF(F15<=0.95,"B","C")) | H15: 0.296 | I15: X | J15: =G15&I15
A16: P0060 | B16: Outdoor Item 060 | C16: Outdoor & Garden | D16: 527769.39 | E16: =D16/SUM($D$5:$D$154) | F16: =SUM($D$5:D16)/SUM($D$5:$D$154) | G16: =IF(F16<=0.8,"A",IF(F16<=0.95,"B","C")) | H16: 0.673 | I16: Y | J16: =G16&I16
A17: P0022 | B17: Electronics Item 022 | C17: Electronics | D17: 483240.74 | E17: =D17/SUM($D$5:$D$154) | F17: =SUM($D$5:D17)/SUM($D$5:$D$154) | G17: =IF(F17<=0.8,"A",IF(F17<=0.95,"B","C")) | H17: 0.287 | I17: X | J17: =G17&I17
A18: P0056 | B18: Outdoor Item 056 | C18: Outdoor & Garden | D18: 426060.76 | E18: =D18/SUM($D$5:$D$154) | F18: =SUM($D$5:D18)/SUM($D$5:$D$154) | G18: =IF(F18<=0.8,"A",IF(F18<=0.95,"B","C")) | H18: 0.395 | I18: X | J18: =G18&I18
A19: P0070 | B19: Outdoor Item 070 | C19: Outdoor & Garden | D19: 420226.79 | E19: =D19/SUM($D$5:$D$154) | F19: =SUM($D$5:D19)/SUM($D$5:$D$154) | G19: =IF(F19<=0.8,"A",IF(F19<=0.95,"B","C")) | H19: 0.399 | I19: X | J19: =G19&I19
... A154: P0146 | B154: Packaging Item 146 | C154: Packaging | D154: 516.71 | E154: =D154/SUM($D$5:$D$154) | F154: =SUM($D$5:D154)/SUM($D$5:$D$154) | G154: =IF(F154<=0.8,"A",IF(F154<=0.95,"B","C")) | H154: 0.923 | I154: Y | J154: =G154&I154

Sheet Supplier Scorecard
A1: Supplier Scorecard (2024-2025, received POs)
A2: Sorted worst OTIF first. Lead-time gap = actual minus promised.
A4: Supplier ID | B4: Supplier | C4: Country | D4: POs received | E4: Promised LT (days) | F4: Actual LT (days) | G4: LT gap (days) | H4: LT std dev | I4: On-time % | J4: In-full % | K4: OTIF % | L4: Avg days late (when late) | M4: Spend ($) | N4: Rating
A5: S04 | B5: Pacific Rim Trading | C5: China | D5: 70 | E5: 35 | F5: 39.6 | G5: =F5-E5 | H5: 7.2 | I5: 0.429 | J5: 0.9 | K5: 0.386 | L5: 8.4 | M5: 513738 | N5: =IF(K5<0.45,"Critical",IF(K5<0.55,"Needs review","Acceptable"))
A6: S09 | B6: Summit Packaging | C6: USA | D6: 196 | E6: 11 | F6: 13.1 | G6: =F6-E6 | H6: 3.8 | I6: 0.469 | J6: 0.862 | K6: 0.408 | L6: 4.4 | M6: 1635559 | N6: =IF(K6<0.45,"Critical",IF(K6<0.55,"Needs review","Acceptable"))
A7: S06 | B7: Prairie Distributors | C7: Canada | D7: 321 | E7: 12 | F7: 13.3 | G7: =F7-E7 | H7: 2.8 | I7: 0.536 | J7: 0.919 | K7: 0.492 | L7: 3.3 | M7: 1073375 | N7: =IF(K7<0.45,"Critical",IF(K7<0.55,"Needs review","Acceptable"))
A8: S07 | B8: Atlantic Imports | C8: USA | D8: 276 | E8: 14 | F8: 14.7 | G8: =F8-E8 | H8: 2.1 | I8: 0.562 | J8: 0.935 | K8: 0.529 | L8: 2.3 | M8: 1441689 | N8: =IF(K8<0.45,"Critical",IF(K8<0.55,"Needs review","Acceptable"))
A9: S02 | B9: Great Lakes Supply | C9: Canada | D9: 262 | E9: 10 | F9: 10.4 | G9: =F9-E9 | H9: 1.5 | I9: 0.576 | J9: 0.939 | K9: 0.538 | L9: 1.8 | M9: 1292572 | N9: =IF(K9<0.45,"Critical",IF(K9<0.55,"Needs review","Acceptable"))
A10: S03 | B10: Rideau Wholesale | C10: Canada | D10: 129 | E10: 5 | F10: 5.1 | G10: =F10-E10 | H10: 0.8 | I10: 0.581 | J10: 0.984 | K10: 0.581 | L10: 1 | M10: 829466 | N10: =IF(K10<0.45,"Critical",IF(K10<0.55,"Needs review","Acceptable"))
A11: S01 | B11: Maple Industrial | C11: Canada | D11: 161 | E11: 7 | F11: 7.1 | G11: =F11-E11 | H11: 1 | I11: 0.602 | J11: 0.969 | K11: 0.59 | L11: 1.2 | M11: 2940245 | N11: =IF(K11<0.45,"Critical",IF(K11<0.55,"Needs review","Acceptable"))
A12: S08 | B12: Northern Parts Co. | C12: Canada | D12: 167 | E12: 9 | F12: 9.1 | G12: =F12-E12 | H12: 1 | I12: 0.611 | J12: 0.964 | K12: 0.593 | L12: 1.2 | M12: 214610 | N12: =IF(K12<0.45,"Critical",IF(K12<0.55,"Needs review","Acceptable"))
A13: S10 | B13: Capital Sourcing | C13: Mexico | D13: 222 | E13: 21 | F13: 21.9 | G13: =F13-E13 | H13: 2.9 | I13: 0.626 | J13: 0.937 | K13: 0.604 | L13: 3.1 | M13: 888086 | N13: =IF(K13<0.45,"Critical",IF(K13<0.55,"Needs review","Acceptable"))
A14: S05 | B14: Laurentian Goods | C14: Canada | D14: 210 | E14: 8 | F14: 8.2 | G14: =F14-E14 | H14: 1.1 | I14: 0.633 | J14: 0.99 | K14: 0.624 | L14: 1.4 | M14: 994243 | N14: =IF(K14<0.45,"Critical",IF(K14<0.55,"Needs review","Acceptable"))

Sheet Stockout Impact
A1: Stockout Impact by Product (2024-2025)
A2: Lost units = demand that arrived while the product was out of stock.
A4: Product ID | B4: Product | C4: Category | D4: ABC | E4: Supplier | F4: Stockout days | G4: Stockout rate | H4: Lost units | I4: Unit price ($) | J4: Est. lost revenue ($) | K4: Turnover | L4: Days of inventory
A5: P0067 | B5: Outdoor Item 067 | C5: Outdoor & Garden | D5: A | E5: S05 | F5: 146 | G5: 0.2 | H5: 4644 | I5: 80.24 | J5: =H5*I5 | K5: 35.402 | L5: 10.31
A6: P0064 | B6: Outdoor Item 064 | C6: Outdoor & Garden | D6: A | E6: S07 | F6: 205 | G6: 0.28 | H6: 1259 | I6: 220.66 | J6: =H6*I6 | K6: 38.85 | L6: 9.395
A7: P0070 | B7: Outdoor Item 070 | C7: Outdoor & Garden | D7: A | E7: S06 | F7: 193 | G7: 0.264 | H7: 2146 | I7: 82.52 | J7: =H7*I7 | K7: 51.386 | L7: 7.103
A8: P0018 | B8: Electronics Item 018 | C8: Electronics | D8: A | E8: S02 | F8: 158 | G8: 0.216 | H8: 939 | I8: 186.41 | J8: =H8*I8 | K8: 30.417 | L8: 12
A9: P0044 | B9: Home Item 044 | C9: Home & Kitchen | D9: A | E9: S09 | F9: 67 | G9: 0.092 | H9: 1386 | I9: 92.71 | J9: =H9*I9 | K9: 16.785 | L9: 21.746
A10: P0059 | B10: Outdoor Item 059 | C10: Outdoor & Garden | D10: B | E10: S10 | F10: 364 | G10: 0.498 | H10: 3795 | I10: 28.62 | J10: =H10*I10 | K10: 49.239 | L10: 7.413
A11: P0019 | B11: Electronics Item 019 | C11: Electronics | D11: A | E11: S01 | F11: 71 | G11: 0.097 | H11: 464 | I11: 232.84 | J11: =H11*I11 | K11: 20.237 | L11: 18.036
A12: P0144 | B12: Packaging Item 144 | C12: Packaging | D12: A | E12: S10 | F12: 217 | G12: 0.297 | H12: 8337 | I12: 8.45 | J12: =H12*I12 | K12: 25.113 | L12: 14.534
A13: P0056 | B13: Outdoor Item 056 | C13: Outdoor & Garden | D13: A | E13: S02 | F13: 71 | G13: 0.097 | H13: 2591 | I13: 24.84 | J13: =H13*I13 | K13: 33.031 | L13: 11.05
A14: P0001 | B14: Electronics Item 001 | C14: Electronics | D14: A | E14: S01 | F14: 25 | G14: 0.034 | H14: 259 | I14: 237.69 | J14: =H14*I14 | K14: 9.701 | L14: 37.626
A15: P0012 | B15: Electronics Item 012 | C15: Electronics | D15: A | E15: S03 | F15: 57 | G15: 0.078 | H15: 303 | I15: 187.01 | J15: =H15*I15 | K15: 21.242 | L15: 17.183
A16: P0003 | B16: Electronics Item 003 | C16: Electronics | D16: A | E16: S06 | F16: 56 | G16: 0.077 | H16: 203 | I16: 244.41 | J16: =H16*I16 | K16: 18.538 | L16: 19.689
... A154: P0146 | B154: Packaging Item 146 | C154: Packaging | D154: C | E154: S02 | F154: 3 | G154: 0.004 | H154: 0 | I154: 2.46 | J154: =H154*I154 | K154: 3.311 | L154: 110.224

Sheet Demand Forecast
A1: 13-Week Demand Forecast (Q1 2026, units)
A2: Model: Ensemble (SN + GBM). Forecasts unconstrained demand, not sales.
A4: Product ID | B4: Product | C4: ABC | D4: Wk 01-04 | E4: Wk 01-11 | F4: Wk 01-18 | G4: Wk 01-25 | H4: Wk 02-01 | I4: Wk 02-08 | J4: Wk 02-15 | K4: Wk 02-22 | L4: Wk 03-01 | M4: Wk 03-08 | N4: Wk 03-15 | O4: Wk 03-22 | P4: Wk 03-29 | Q4: Q1 total
A5: P0001 | B5: Electronics Item 001 | C5: A | D5: 95.2 | E5: 96.8 | F5: 94 | G5: 94 | H5: 95.1 | I5: 77.9 | J5: 92 | K5: 90.4 | L5: 97.4 | M5: 96.2 | N5: 95.9 | O5: 108.3 | P5: 83.2 | Q5: =SUM(D5:P5)
A6: P0002 | B6: Electronics Item 002 | C6: A | D6: 41.3 | E6: 50.7 | F6: 45 | G6: 37.4 | H6: 42.7 | I6: 36.1 | J6: 44.7 | K6: 39.9 | L6: 44.6 | M6: 41.5 | N6: 50 | O6: 50.5 | P6: 40.5 | Q6: =SUM(D6:P6)
A7: P0003 | B7: Electronics Item 003 | C7: A | D7: 27.4 | E7: 26.4 | F7: 25 | G7: 20.7 | H7: 28.5 | I7: 27.3 | J7: 27.3 | K7: 23.2 | L7: 20 | M7: 23.7 | N7: 22.7 | O7: 24.8 | P7: 24.7 | Q7: =SUM(D7:P7)
A8: P0004 | B8: Electronics Item 004 | C8: A | D8: 10.7 | E8: 8.2 | F8: 9.1 | G8: 8.4 | H8: 9.7 | I8: 8 | J8: 9.8 | K8: 9.7 | L8: 13.8 | M8: 9.8 | N8: 10 | O8: 9.1 | P8: 9.8 | Q8: =SUM(D8:P8)
A9: P0005 | B9: Electronics Item 005 | C9: B | D9: 3.4 | E9: 4.6 | F9: 6.2 | G9: 2.7 | H9: 4.6 | I9: 4.6 | J9: 4.6 | K9: 6.7 | L9: 6.1 | M9: 6.3 | N9: 5.3 | O9: 1.9 | P9: 6.8 | Q9: =SUM(D9:P9)
A10: P0006 | B10: Electronics Item 006 | C10: A | D10: 44 | E10: 35.5 | F10: 36.9 | G10: 32 | H10: 32.9 | I10: 33 | J10: 39.4 | K10: 39.4 | L10: 36.1 | M10: 36.6 | N10: 36.4 | O10: 33.9 | P10: 36 | Q10: =SUM(D10:P10)
A11: P0007 | B11: Electronics Item 007 | C11: A | D11: 36.6 | E11: 33.8 | F11: 39.1 | G11: 34.9 | H11: 39.4 | I11: 41 | J11: 36.6 | K11: 39.3 | L11: 35.9 | M11: 30.6 | N11: 32 | O11: 41.1 | P11: 41.1 | Q11: =SUM(D11:P11)
A12: P0008 | B12: Electronics Item 008 | C12: C | D12: 4 | E12: 4.8 | F12: 3.1 | G12: 4.8 | H12: 4.8 | I12: 3.9 | J12: 3 | K12: 4.8 | L12: 5.5 | M12: 3.9 | N12: 6.8 | O12: 6.8 | P12: 1.9 | Q12: =SUM(D12:P12)
A13: P0009 | B13: Electronics Item 009 | C13: B | D13: 14.5 | E13: 13.1 | F13: 9.1 | G13: 10.2 | H13: 12.1 | I13: 12 | J13: 8.7 | K13: 8.7 | L13: 9.1 | M13: 13.4 | N13: 10.2 | O13: 12.4 | P13: 11.8 | Q13: =SUM(D13:P13)
A14: P0010 | B14: Electronics Item 010 | C14: B | D14: 12.8 | E14: 11.4 | F14: 14.7 | G14: 13.6 | H14: 11.5 | I14: 13.6 | J14: 14 | K14: 12.7 | L14: 13.5 | M14: 14.2 | N14: 20.4 | O14: 14 | P14: 14.2 | Q14: =SUM(D14:P14)
A15: P0011 | B15: Electronics Item 011 | C15: C | D15: 1.6 | E15: 1.4 | F15: 1.5 | G15: 1.2 | H15: 1.1 | I15: 2 | J15: 1.2 | K15: 1.2 | L15: 1.2 | M15: 1.5 | N15: 1.2 | O15: 1.1 | P15: 1.2 | Q15: =SUM(D15:P15)
A16: P0012 | B16: Electronics Item 012 | C16: A | D16: 38.7 | E16: 38.1 | F16: 54.8 | G16: 43.3 | H16: 40.3 | I16: 51.6 | J16: 41.4 | K16: 36.4 | L16: 43 | M16: 43.2 | N16: 31.4 | O16: 44.2 | P16: 42 | Q16: =SUM(D16:P16)
... A154: P0150 | B154: Packaging Item 150 | C154: C | D154: 68.9 | E154: 68.9 | F154: 72.4 | G154: 71.1 | H154: 64.1 | I154: 69 | J154: 70.6 | K154: 73 | L154: 70.3 | M154: 67.6 | N154: 66.1 | O154: 62.3 | P154: 67.5 | Q154: =SUM(D154:P154)
A155: Total | D155: =SUM(D5:D154) | E155: =SUM(E5:E154) | F155: =SUM(F5:F154) | G155: =SUM(G5:G154) | H155: =SUM(H5:H154) | I155: =SUM(I5:I154) | J155: =SUM(J5:J154) | K155: =SUM(K5:K154) | ... Q155: =SUM(Q5:Q154)
A157: Backtest accuracy (Q4 2025 holdout, lower WAPE is better)
A158: Model | B158: WAPE all | C158: Bias | D158: WAPE A | E158: WAPE B | F158: WAPE C
A159: Naive (8-wk avg) | B159: 0.31819139 | C159: -0.071827074 | D159: 0.27093411 | E159: 0.36159442 | F159: 0.37584275
A160: Seasonal naive | B160: 0.19502199 | C160: 0.035622299 | D160: 0.15312688 | E160: 0.18500762 | F160: 0.33823128
A161: Gradient boosting | B161: 0.25535615 | C161: -0.041228678 | D161: 0.19084181 | E161: 0.28645502 | F161: 0.38753121
A162: Ensemble (SN + GBM) | B162: 0.18688134 | C162: -0.0028031895 | D162: 0.13867162 | E162: 0.19976082 | F162: 0.30532786

Sheet Policy Backtest
A1: 2025 Back-test: Current vs Optimized Policy
A2: Optimized policy simulated on actual 2025 demand with replayed supplier lead times. Parameters refreshed monthly, no look-ahead.
A4: Metric | B4: Current policy | C4: Optimized policy | D4: Change | E4: Change %
A5: Stockout rate (% of SKU-days) | B5: 0.0626 | C5: 0.0075 | D5: =C5-B5 | E5: =IF(B5=0,0,D5/B5)
A6: Fill rate (% of demand met) | B6: 0.9284 | C6: 0.9905 | D6: =C6-B6 | E6: =IF(B6=0,0,D6/B6)
A7: Lost units | B7: 27372 | C7: 2227 | D7: =C7-B7 | E7: =IF(B7=0,0,D7/B7)
A8: Est. lost revenue ($) | B8: 1309737.4 | C8: 90355.81 | D8: =C8-B8 | E8: =IF(B8=0,0,D8/B8)
A9: Est. lost gross profit ($) | B9: 551936.15 | C9: 34682.69 | D9: =C9-B9 | E9: =IF(B9=0,0,D9/B9)
A10: Avg inventory value ($) | B10: 538087.6 | C10: 512248.18 | D10: =C10-B10 | E10: =IF(B10=0,0,D10/B10)
A11: Annual carrying cost @25% ($) | B11: 134521.9 | C11: 128062.05 | D11: =C11-B11 | E11: =IF(B11=0,0,D11/B11)
A12: Purchase orders placed | B12: 1070 | C12: 894 | D12: =C12-B12 | E12: =IF(B12=0,0,D12/B12)
A13: Ordering cost @$75/PO ($) | B13: 80250 | C13: 67050 | D13: =C13-B13 | E13: =IF(B13=0,0,D13/B13)

Sheet Data Cleaning Log
A1: Data Cleaning Log
A2: Every correction applied by src/02_clean_data.py.
A4: Table | B4: Issue | C4: Rows affected | D4: Action
A5: products | B5: Inconsistent category casing / trailing spaces | C5: 15 | D5: Trimmed and title-cased
A6: sales | B6: Exact duplicate rows | C6: 531 | D6: Removed
A7: sales | B7: Non-ISO date format (DD/MM/YYYY) | C7: 2665 | D7: Parsed to ISO date
A8: sales | B8: Zero/negative quantity (entry errors, not tagged as returns) | C8: 60 | D8: Removed
A9: sales | B9: Extreme quantity outliers (>5x product's 99th pct) | C9: 8 | D9: Removed
A10: sales | B10: Missing unit_price | C10: 400 | D10: Imputed with product list price
A11: sales | B11: Rows in -> rows out | C11: 599 | D11: 133,295 -> 132,696
A12: purchase_orders | B12: Open POs (not yet received at period end) | C12: 36 | D12: Kept, excluded from delivery KPIs
